mindaugas_enhanced_print/__init__.py
mindaugas_enhanced_print/printer.py
mindaugas_enhanced_print-0.0.2.dist-info/LICENSE
mindaugas_enhanced_print-0.0.2.dist-info/METADATA
mindaugas_enhanced_print-0.0.2.dist-info/WHEEL
mindaugas_enhanced_print-0.0.2.dist-info/top_level.txt
mindaugas_enhanced_print-0.0.2.dist-info/RECORD
